skater/__init__.py
skater/about.py
skater/core/__init__.py
skater/core/explanations.py
skater/core/model_interpreter.py
skater/core/global_interpretation/__init__.py
skater/core/global_interpretation/base.py
skater/core/global_interpretation/feature_importance.py
skater/core/global_interpretation/partial_dependence.py
skater/core/local_interpretation/__init__.py
skater/core/local_interpretation/text_interpreter.py
skater/core/local_interpretation/lime/__init__.py
skater/core/local_interpretation/lime/lime_image.py
skater/core/local_interpretation/lime/lime_tabular.py
skater/core/local_interpretation/lime/lime_text.py
skater/core/visualizer/__init__.py
skater/core/visualizer/relevance_visualizer.py
skater/data/__init__.py
skater/data/datamanager.py
skater/model/__init__.py
skater/model/base.py
skater/model/deployed_model.py
skater/model/local_model.py
skater/model/scorer.py
skater/tests/__init__.py
skater/tests/all_tests.py
skater/tests/arg_parser.py
skater/tests/test_data.py
skater/tests/test_feature_importance.py
skater/tests/test_lime.py
skater/tests/test_model.py
skater/tests/test_partial_dependence.py
skater/tests/test_text_interpreter.py
skater/tests/util/__init__.py
skater/tests/util/build_example.py
skater/util/__init__.py
skater/util/dataops.py
skater/util/exceptions.py
skater/util/kernels.py
skater/util/logger.py
skater/util/plotting.py
skater/util/progressbar.py
skater/util/serialization.py
skater/util/static_types.py
skater/util/user_defined_types.py
skater-1.0.3.dist-info/DESCRIPTION.rst
skater-1.0.3.dist-info/METADATA
skater-1.0.3.dist-info/RECORD
skater-1.0.3.dist-info/WHEEL
skater-1.0.3.dist-info/metadata.json
skater-1.0.3.dist-info/top_level.txt
