Metadata-Version: 2.0
Name: skater
Version: 1.0.3
Summary: Model Agnostic Interpretation Library
Home-page: https://github.com/datascienceinc/skater/
Author: Aaron Kramer, DataScience.com Team, Pramit Choudhary
Author-email: dstm@datascience.com
License: MIT
Platform: UNKNOWN
Requires-Dist: dill (>=0.2.6)
Requires-Dist: ds-lime (>=0.1.1.21)
Requires-Dist: multiprocess
Requires-Dist: pandas (>=0.19)
Requires-Dist: requests
Requires-Dist: scikit-learn (>=0.18)
Provides-Extra: all
Requires-Dist: matplotlib; extra == 'all'
